pytractor/__init__.py
pytractor/exceptions.py
pytractor/mixins.py
pytractor/webdriver.py
pytractor/protractor/extracted/allowAnimations.js
pytractor/protractor/extracted/evaluate.js
pytractor/protractor/extracted/findAllRepeaterRows.js
pytractor/protractor/extracted/findBindings.js
pytractor/protractor/extracted/findByButtonText.js
pytractor/protractor/extracted/findByCssContainingText.js
pytractor/protractor/extracted/findByModel.js
pytractor/protractor/extracted/findByOptions.js
pytractor/protractor/extracted/findByPartialButtonText.js
pytractor/protractor/extracted/findRepeaterColumn.js
pytractor/protractor/extracted/findRepeaterElement.js
pytractor/protractor/extracted/findRepeaterRows.js
pytractor/protractor/extracted/getLocationAbsUrl.js
pytractor/protractor/extracted/getPendingHttpRequests.js
pytractor/protractor/extracted/installInBrowser.js
pytractor/protractor/extracted/setLocation.js
pytractor/protractor/extracted/testForAngular.js
pytractor/protractor/extracted/waitForAngular.js
pytractor/tests/__init__.py
pytractor/tests/functional/__init__.py
pytractor/tests/functional/test_base.py
pytractor/tests/functional/test_helpers.py
pytractor/tests/functional/test_locators.py
pytractor/tests/functional/test_wait.py
pytractor/tests/functional/test_webdriver.py
pytractor/tests/functional/testdriver.py
pytractor/tests/functional/testserver.py
pytractor/tests/functional/testapp/LICENSE
pytractor/tests/functional/testapp/alt_root_index.html
pytractor/tests/functional/testapp/app.css
pytractor/tests/functional/testapp/app.js
pytractor/tests/functional/testapp/favicon.ico
pytractor/tests/functional/testapp/index-no-angular.html
pytractor/tests/functional/testapp/index.html
pytractor/tests/functional/testapp/login.html
pytractor/tests/functional/testapp/animation/animation.css
pytractor/tests/functional/testapp/animation/animation.html
pytractor/tests/functional/testapp/animation/animation.js
pytractor-0.2.1.dist-info/DESCRIPTION.rst
pytractor-0.2.1.dist-info/METADATA
pytractor-0.2.1.dist-info/RECORD
pytractor-0.2.1.dist-info/WHEEL
pytractor-0.2.1.dist-info/metadata.json
pytractor-0.2.1.dist-info/top_level.txt
