Metadata-Version: 2.0
Name: pytractor
Version: 0.2.1
Summary: Selenium testing for Angular.js apps
Home-page: https://github.com/kpodl/pytractor
Author: Konrad Podloucky
Author-email: konrad+pytractor@crunchy-frog.org
License: Apache 2.0
Keywords: selenium angular.js testing
Platform: UNKNOWN
Classifier: Development Status :: 3 - Alpha
Classifier: Intended Audience :: Developers
Classifier: Topic :: Software Development :: Testing
Classifier: License :: OSI Approved :: Apache Software License
Classifier: Programming Language :: Python :: 2.7
Requires-Dist: future (>=0.15.2)
Requires-Dist: selenium (>=2.48.0)
